[
 {
   "A": "Lilian Kakai",
   "B": "0714034985"
 },
 {
   "A": "Gladys Andia",
   "B": "0729618876"
 },
 {
   "A": "Evelyne Astiaya",
   "B": "0714642752"
 },
 {
   "A": "Nancy I Onyino",
   "B": "0722374638"
 },
 {
   "A": "Norah M Gibendi",
   "B": "0724108325"
 },
 {
   "A": "Gabriel Ogol Nydwa",
   "B": "0711223887"
 },
 {
   "A": "Carlos Okoth Awuor",
   "B": "0722415823"
 },
 {
   "A": "Victor Onyango",
   "B": "0714652502"
 },
 {
   "A": "Donald Omondi",
   "B": "0720354263"
 },
 {
   "A": "George Apollo Omondi",
   "B": "0718249179"
 },
 {
   "A": "David Wakhabu",
   "B": "0729219424"
 },
 {
   "A": "Wycliffe Wasike",
   "B": "0704375023"
 },
 {
   "A": "Gladys M. Tenge",
   "B": "0729978457"
 },
 {
   "A": "Silas Kimachasi",
   "B": "0728546807"
 },
 {
   "A": "Justus Kimai",
   "B": "0715880411"
 },
 {
   "A": "Simon Odinga",
   "B": "0712499041"
 },
 {
   "A": "Millicent Namana",
   "B": "0712146070"
 },
 {
   "A": "Martin Nyongesa",
   "B": "0701662359"
 },
 {
   "A": "Selina Atako",
   "B": "0720387893"
 },
 {
   "A": "George Ochieng Mang'ira",
   "B": "0721479196"
 },
 {
   "A": "Willam Makotsi",
   "B": "0710454598"
 },
 {
   "A": "Julius Ageng'o",
   "B": "0710551743"
 },
 {
   "A": "Hudson Mulonga",
   "B": "0721710533"
 },
 {
   "A": "Timothy Chalamba",
   "B": "0720829874"
 },
 {
   "A": "Enos Chegero",
   "B": "0700381799"
 },
 {
   "A": "Fanuel Ndori",
   "B": "0722628542"
 },
 {
   "A": "Peter obunga",
   "B": "0720228539"
 },
 {
   "A": "Allan Metho",
   "B": "0722613765"
 },
 {
   "A": "Kelvin Kagola",
   "B": "0712583352"
 },
 {
   "A": "Jacob Onyango",
   "B": "0721339659"
 },
 {
   "A": "George Olum",
   "B": "0703244583"
 },
 {
   "A": "Agnes Nafula",
   "B": "0722449294"
 },
 {
   "A": "Emanuel KisakaKakai",
   "B": "0701028828"
 },
 {
   "A": "Oscar Nabiswa Kaphuka",
   "B": "0712216434"
 },
 {
   "A": "Danstan Watila",
   "B": "0728435731"
 },
 {
   "A": "Timothy Ohutso",
   "B": "0729263250"
 },
 {
   "A": "Churchil Oriko",
   "B": "0710952451"
 },
 {
   "A": "Peres Nandi",
   "B": "0713096929"
 },
 {
   "A": "Jerry Aluoch",
   "B": "0721224514"
 },
 {
   "A": "Elisha Kuloba",
   "B": "0729719589"
 },
 {
   "A": "Silas Barasa",
   "B": "0792285051"
 },
 {
   "A": "Mary Wambulwa",
   "B": "0728431548"
 },
 {
   "A": "Salome Watulo",
   "B": "0725906379"
 },
 {
   "A": "Mariam Musundi",
   "B": "0710496420"
 },
 {
   "A": "Consolata Namulanda",
   "B": "0710774736"
 },
 {
   "A": "Eglays Amakobe",
   "B": "0726099456"
 },
 {
   "A": "Santilino Omajani",
   "B": "0702808256"
 },
 {
   "A": "Jane Ndalo",
   "B": "0710125730"
 },
 {
   "A": "Benard Okello",
   "B": "0787489099"
 },
 {
   "A": "Elisha Nyawara",
   "B": "0701400611"
 },
 {
   "A": "Chris Adhola",
   "B": "0725718279"
 },
 {
   "A": "Willis Opiata",
   "B": "0724370355"
 },
 {
   "A": "William Onditi",
   "B": "0715824596"
 },
 {
   "A": "James Ayuaya",
   "B": "0716659866"
 },
 {
   "A": "Vincent Agidho",
   "B": "0712402317"
 },
 {
   "A": "Richard Olweny",
   "B": "0721654369"
 },
 {
   "A": "Risper Denge",
   "B": "0724303959"
 },
 {
   "A": "John Onyango",
   "B": "0719865952"
 },
 {
   "A": "Elvis Ouma",
   "B": "0717302636"
 },
 {
   "A": "Winstela Kimoi",
   "B": "0717302636"
 },
 {
   "A": "Charles Ogolla",
   "B": "0720038277"
 },
 {
   "A": "Maxwel Ouma",
   "B": "07103133878"
 },
 {
   "A": "Consolata Omollo",
   "B": "0722767829"
 },
 {
   "A": "Phoebe Ouma",
   "B": "0711534537"
 },
 {
   "A": "Esdor Omondi",
   "B": "0700062017"
 },
 {
   "A": "Ledwina Achieng’ Olemo",
   "B": "0719183443"
 },
 {
   "A": "George Amollo",
   "B": "0703678906"
 },
 {
   "A": "Joseph Owuor",
   "B": "0724441198"
 },
 {
   "A": "Kennedy Onyango Odula",
   "B": "0720813585"
 },
 {
   "A": "Charles Otieno",
   "B": "0719456029"
 },
 {
   "A": "Patrick Onyango Odhiambo",
   "B": "0717899189"
 },
 {
   "A": "Jared Odoyo",
   "B": "0727115077"
 },
 {
   "A": "Evance Odiwuor",
   "B": "0714065350"
 },
 {
   "A": "Sana Samuel",
   "B": "0720943397"
 },
 {
   "A": "Otiep",
   "B": "0728946614"
 },
 {
   "A": "Ombok Gilbert",
   "B": "0722480520"
 },
 {
   "A": "Samuel Oguma",
   "B": "0738231748"
 },
 {
   "A": "Flora Ovamba",
   "B": "0729168721"
 },
 {
   "A": "Catherine Ijuza",
   "B": "0724071873"
 },
 {
   "A": "David Ingoi",
   "B": "0720341985"
 },
 {
   "A": "James Chiluyi",
   "B": "0711426485"
 },
 {
   "A": "Isaac Mukwenyi",
   "B": "0708545059"
 },
 {
   "A": "Josphine Muchele",
   "B": "0712253689"
 },
 {
   "A": "Stella Aura N.",
   "B": "0728580750"
 },
 {
   "A": "Rose Mutete",
   "B": "0727353842"
 },
 {
   "A": "Evans Starnely",
   "B": "0725152636"
 },
 {
   "A": "Edward Odongo",
   "B": "0702274218"
 },
 {
   "A": "Gelas Wafula",
   "B": "0719470170"
 },
 {
   "A": "Misiko Sammy",
   "B": "0712284543"
 },
 {
   "A": "Shadrack Oduor",
   "B": "0712284543"
 },
 {
   "A": "Hassan Ngaiwa",
   "B": "0724142170"
 },
 {
   "A": "Anorld Ochieng",
   "B": "0721112048"
 },
 {
   "A": "Khalayi Winny",
   "B": "0702697776"
 },
 {
   "A": "Metrine Makokha",
   "B": "0713849825"
 },
 {
   "A": "Pamela Wanyama",
   "B": "0719845051"
 },
 {
   "A": "Beatrice Waremia",
   "B": "0716563432"
 },
 {
   "A": "Thomas Manuar",
   "B": "0712649398"
 },
 {
   "A": "Ombok David",
   "B": "0795829119"
 },
 {
   "A": "Rose Muga",
   "B": "0708233645"
 },
 {
   "A": "Alphonce Oganda",
   "B": "0791005944"
 },
 {
   "A": "Protus Nazunshi",
   "B": "0723919301"
 },
 {
   "A": "Rozina Awino",
   "B": "0718238388"
 },
 {
   "A": "Violet Angawa",
   "B": "0707338208"
 },
 {
   "A": "Julius A.Shihundu",
   "B": "0791232905"
 },
 {
   "A": "Julius Wakhungu",
   "B": "0710272590"
 },
 {
   "A": "Charles onyango",
   "B": "0700355031"
 },
 {
   "A": "Alex Afubwa",
   "B": "0728998029"
 },
 {
   "A": "Justus Makokha",
   "B": "0725154170"
 },
 {
   "A": "Jotham Munala",
   "B": "0714573725"
 },
 {
   "A": "Catherine Okumu",
   "B": "0725469375"
 },
 {
   "A": "Benard Otieno",
   "B": "0703942518"
 },
 {
   "A": "Jactor Gathius",
   "B": "0725154170"
 },
 {
   "A": "Mwita Itembe",
   "B": "0725797177"
 },
 {
   "A": "George obiero",
   "B": "0736996719"
 },
 {
   "A": "Mildred Otieno",
   "B": "0720430099"
 },
 {
   "A": "Pius Mutimba",
   "B": "0704857263"
 },
 {
   "A": "Sarah Lutta",
   "B": "0728159999"
 },
 {
   "A": "Charles Wandako",
   "B": "0723160267"
 },
 {
   "A": "Tafline Night",
   "B": "0720892057"
 },
 {
   "A": "Onyango Juma",
   "B": "0702275571"
 },
 {
   "A": "Julius Buyuni",
   "B": "0712076645"
 },
 {
   "A": "Nick Okello",
   "B": "0722346808"
 },
 {
   "A": "Joshep O.Maganda",
   "B": "0702345928"
 },
 {
   "A": "Peter M. Boke",
   "B": "0722161296"
 },
 {
   "A": "Benta Otieno",
   "B": "0725988797"
 },
 {
   "A": "Dickens Odanga",
   "B": "0727032462"
 },
 {
   "A": "Evans Wekhomba",
   "B": "0723363464"
 },
 {
   "A": "Lawrence Oluoch",
   "B": "0715423528"
 },
 {
   "A": "Mary Odhiambo",
   "B": "0710109285"
 },
 {
   "A": "",
   "B": ""
 },
 {
   "A": "",
   "B": ""
 },
 {
   "A": "",
   "B": ""
 },
 {
   "A": "",
   "B": ""
 },
 {
   "A": "",
   "B": ""
 },
 {
   "A": "",
   "B": ""
 },
 {
   "A": "",
   "B": ""
 },
 {
   "A": "",
   "B": ""
 },
 {
   "A": "",
   "B": ""
 },
 {
   "A": "",
   "B": ""
 },
 {
   "A": "",
   "B": ""
 },
 {
   "A": "",
   "B": ""
 },
 {
   "A": "",
   "B": ""
 },
 {
   "A": "",
   "B": ""
 },
 {
   "A": "",
   "B": ""
 },
 {
   "A": "",
   "B": ""
 },
 {
   "A": "",
   "B": ""
 },
 {
   "A": "",
   "B": ""
 },
 {
   "A": "",
   "B": ""
 },
 {
   "A": "",
   "B": ""
 },
 {
   "A": "",
   "B": ""
 },
 {
   "A": "",
   "B": ""
 },
 {
   "A": "",
   "B": ""
 },
 {
   "A": "",
   "B": ""
 },
 {
   "A": "",
   "B": ""
 },
 {
   "A": "",
   "B": ""
 },
 {
   "A": "",
   "B": ""
 },
 {
   "A": "",
   "B": ""
 },
 {
   "A": "",
   "B": ""
 },
 {
   "A": "",
   "B": ""
 },
 {
   "A": "",
   "B": ""
 },
 {
   "A": "",
   "B": ""
 },
 {
   "A": "",
   "B": ""
 },
 {
   "A": "",
   "B": ""
 },
 {
   "A": "",
   "B": ""
 },
 {
   "A": "",
   "B": ""
 },
 {
   "A": "",
   "B": ""
 },
 {
   "A": "",
   "B": ""
 },
 {
   "A": "",
   "B": ""
 },
 {
   "A": "",
   "B": ""
 },
 {
   "A": "",
   "B": ""
 },
 {
   "A": "",
   "B": ""
 },
 {
   "A": "",
   "B": ""
 },
 {
   "A": "",
   "B": ""
 },
 {
   "A": "",
   "B": ""
 },
 {
   "A": "",
   "B": ""
 },
 {
   "A": "",
   "B": ""
 },
 {
   "A": "",
   "B": ""
 },
 {
   "A": "",
   "B": ""
 },
 {
   "A": "",
   "B": ""
 },
 {
   "A": "",
   "B": ""
 },
 {
   "A": "",
   "B": ""
 },
 {
   "A": "",
   "B": ""
 },
 {
   "A": "",
   "B": ""
 },
 {
   "A": "",
   "B": ""
 },
 {
   "A": "",
   "B": ""
 },
 {
   "A": "",
   "B": ""
 },
 {
   "A": "",
   "B": ""
 },
 {
   "A": "",
   "B": ""
 },
 {
   "A": "",
   "B": ""
 },
 {
   "A": "",
   "B": ""
 },
 {
   "A": "",
   "B": ""
 },
 {
   "A": "",
   "B": ""
 },
 {
   "A": "",
   "B": ""
 },
 {
   "A": "",
   "B": ""
 },
 {
   "A": "",
   "B": ""
 },
 {
   "A": "",
   "B": ""
 },
 {
   "A": "",
   "B": ""
 },
 {
   "A": "",
   "B": ""
 },
 {
   "A": "",
   "B": ""
 },
 {
   "A": "",
   "B": ""
 },
 {
   "A": "",
   "B": ""
 },
 {
   "A": "",
   "B": ""
 },
 {
   "A": "",
   "B": ""
 },
 {
   "A": "",
   "B": ""
 },
 {
   "A": "",
   "B": ""
 },
 {
   "A": "",
   "B": ""
 },
 {
   "A": "",
   "B": ""
 },
 {
   "A": "",
   "B": ""
 },
 {
   "A": "",
   "B": ""
 },
 {
   "A": "",
   "B": ""
 },
 {
   "A": "",
   "B": ""
 },
 {
   "A": "",
   "B": ""
 },
 {
   "A": "",
   "B": ""
 },
 {
   "A": "",
   "B": ""
 },
 {
   "A": "",
   "B": ""
 },
 {
   "A": "",
   "B": ""
 },
 {
   "A": "",
   "B": ""
 },
 {
   "A": "",
   "B": ""
 },
 {
   "A": "",
   "B": ""
 },
 {
   "A": "",
   "B": ""
 },
 {
   "A": "",
   "B": ""
 },
 {
   "A": "",
   "B": ""
 },
 {
   "A": "",
   "B": ""
 },
 {
   "A": "",
   "B": ""
 },
 {
   "A": "",
   "B": ""
 },
 {
   "A": "",
   "B": ""
 },
 {
   "A": "",
   "B": ""
 },
 {
   "A": "",
   "B": ""
 },
 {
   "A": "",
   "B": ""
 },
 {
   "A": "",
   "B": ""
 },
 {
   "A": "",
   "B": ""
 },
 {
   "A": "",
   "B": ""
 },
 {
   "A": "",
   "B": ""
 },
 {
   "A": "",
   "B": ""
 },
 {
   "A": "",
   "B": ""
 },
 {
   "A": "",
   "B": ""
 },
 {
   "A": "",
   "B": ""
 },
 {
   "A": "",
   "B": ""
 },
 {
   "A": "",
   "B": ""
 },
 {
   "A": "",
   "B": ""
 },
 {
   "A": "",
   "B": ""
 },
 {
   "A": "",
   "B": ""
 },
 {
   "A": "",
   "B": ""
 },
 {
   "A": "",
   "B": ""
 },
 {
   "A": "",
   "B": ""
 },
 {
   "A": "",
   "B": ""
 },
 {
   "A": "",
   "B": ""
 },
 {
   "A": "",
   "B": ""
 },
 {
   "A": "",
   "B": ""
 },
 {
   "A": "",
   "B": ""
 },
 {
   "A": "",
   "B": ""
 },
 {
   "A": "",
   "B": ""
 },
 {
   "A": "",
   "B": ""
 },
 {
   "A": "",
   "B": ""
 },
 {
   "A": "",
   "B": ""
 },
 {
   "A": "",
   "B": ""
 },
 {
   "A": "",
   "B": ""
 },
 {
   "A": "",
   "B": ""
 },
 {
   "A": "",
   "B": ""
 },
 {
   "A": "",
   "B": ""
 },
 {
   "A": "",
   "B": ""
 },
 {
   "A": "",
   "B": ""
 },
 {
   "A": "",
   "B": ""
 },
 {
   "A": "",
   "B": ""
 },
 {
   "A": "",
   "B": ""
 },
 {
   "A": "",
   "B": ""
 },
 {
   "A": "",
   "B": ""
 },
 {
   "A": "",
   "B": ""
 },
 {
   "A": "",
   "B": ""
 },
 {
   "A": "",
   "B": ""
 },
 {
   "A": "",
   "B": ""
 },
 {
   "A": "",
   "B": ""
 },
 {
   "A": "",
   "B": ""
 },
 {
   "A": "",
   "B": ""
 },
 {
   "A": "",
   "B": ""
 },
 {
   "A": "",
   "B": ""
 },
 {
   "A": "",
   "B": ""
 },
 {
   "A": "",
   "B": ""
 },
 {
   "A": "",
   "B": ""
 },
 {
   "A": "",
   "B": ""
 },
 {
   "A": "",
   "B": ""
 },
 {
   "A": "",
   "B": ""
 },
 {
   "A": "",
   "B": ""
 },
 {
   "A": "",
   "B": ""
 },
 {
   "A": "",
   "B": ""
 },
 {
   "A": "",
   "B": ""
 },
 {
   "A": "",
   "B": ""
 },
 {
   "A": "",
   "B": ""
 },
 {
   "A": "",
   "B": ""
 },
 {
   "A": "",
   "B": ""
 },
 {
   "A": "",
   "B": ""
 },
 {
   "A": "",
   "B": ""
 },
 {
   "A": "",
   "B": ""
 },
 {
   "A": "",
   "B": ""
 },
 {
   "A": "",
   "B": ""
 },
 {
   "A": "",
   "B": ""
 },
 {
   "A": "",
   "B": ""
 },
 {
   "A": "",
   "B": ""
 },
 {
   "A": "",
   "B": ""
 },
 {
   "A": "",
   "B": ""
 },
 {
   "A": "",
   "B": ""
 },
 {
   "A": "",
   "B": ""
 },
 {
   "A": "",
   "B": ""
 },
 {
   "A": "",
   "B": ""
 },
 {
   "A": "",
   "B": ""
 },
 {
   "A": "",
   "B": ""
 },
 {
   "A": "",
   "B": ""
 },
 {
   "A": "",
   "B": ""
 },
 {
   "A": "",
   "B": ""
 },
 {
   "A": "",
   "B": ""
 },
 {
   "A": "",
   "B": ""
 },
 {
   "A": "",
   "B": ""
 },
 {
   "A": "",
   "B": ""
 },
 {
   "A": "",
   "B": ""
 },
 {
   "A": "",
   "B": ""
 },
 {
   "A": "",
   "B": ""
 },
 {
   "A": "",
   "B": ""
 },
 {
   "A": "",
   "B": ""
 },
 {
   "A": "",
   "B": ""
 },
 {
   "A": "",
   "B": ""
 },
 {
   "A": "",
   "B": ""
 },
 {
   "A": "",
   "B": ""
 },
 {
   "A": "",
   "B": ""
 },
 {
   "A": "",
   "B": ""
 },
 {
   "A": "",
   "B": ""
 },
 {
   "A": "",
   "B": ""
 },
 {
   "A": "",
   "B": ""
 },
 {
   "A": "",
   "B": ""
 },
 {
   "A": "",
   "B": ""
 },
 {
   "A": "",
   "B": ""
 },
 {
   "A": "",
   "B": ""
 },
 {
   "A": "",
   "B": ""
 },
 {
   "A": "",
   "B": ""
 },
 {
   "A": "",
   "B": ""
 },
 {
   "A": "",
   "B": ""
 },
 {
   "A": "",
   "B": ""
 },
 {
   "A": "",
   "B": ""
 },
 {
   "A": "",
   "B": ""
 },
 {
   "A": "",
   "B": ""
 },
 {
   "A": "",
   "B": ""
 },
 {
   "A": "",
   "B": ""
 },
 {
   "A": "",
   "B": ""
 },
 {
   "A": "",
   "B": ""
 },
 {
   "A": "",
   "B": ""
 },
 {
   "A": "",
   "B": ""
 },
 {
   "A": "",
   "B": ""
 },
 {
   "A": "",
   "B": ""
 },
 {
   "A": "",
   "B": ""
 },
 {
   "A": "",
   "B": ""
 },
 {
   "A": "",
   "B": ""
 },
 {
   "A": "",
   "B": ""
 },
 {
   "A": "",
   "B": ""
 },
 {
   "A": "",
   "B": ""
 },
 {
   "A": "",
   "B": ""
 },
 {
   "A": "",
   "B": ""
 },
 {
   "A": "",
   "B": ""
 },
 {
   "A": "",
   "B": ""
 },
 {
   "A": "",
   "B": ""
 },
 {
   "A": "",
   "B": ""
 },
 {
   "A": "",
   "B": ""
 },
 {
   "A": "",
   "B": ""
 },
 {
   "A": "",
   "B": ""
 },
 {
   "A": "",
   "B": ""
 },
 {
   "A": "",
   "B": ""
 },
 {
   "A": "",
   "B": ""
 },
 {
   "A": "",
   "B": ""
 },
 {
   "A": "",
   "B": ""
 },
 {
   "A": "",
   "B": ""
 },
 {
   "A": "",
   "B": ""
 },
 {
   "A": "",
   "B": ""
 },
 {
   "A": "",
   "B": ""
 },
 {
   "A": "",
   "B": ""
 },
 {
   "A": "",
   "B": ""
 },
 {
   "A": "",
   "B": ""
 },
 {
   "A": "",
   "B": ""
 },
 {
   "A": "",
   "B": ""
 },
 {
   "A": "",
   "B": ""
 },
 {
   "A": "",
   "B": ""
 },
 {
   "A": "",
   "B": ""
 },
 {
   "A": "",
   "B": ""
 },
 {
   "A": "",
   "B": ""
 },
 {
   "A": "",
   "B": ""
 },
 {
   "A": "",
   "B": ""
 },
 {
   "A": "",
   "B": ""
 },
 {
   "A": "",
   "B": ""
 },
 {
   "A": "",
   "B": ""
 },
 {
   "A": "",
   "B": ""
 },
 {
   "A": "",
   "B": ""
 },
 {
   "A": "",
   "B": ""
 },
 {
   "A": "",
   "B": ""
 },
 {
   "A": "",
   "B": ""
 },
 {
   "A": "",
   "B": ""
 },
 {
   "A": "",
   "B": ""
 },
 {
   "A": "",
   "B": ""
 },
 {
   "A": "",
   "B": ""
 },
 {
   "A": "",
   "B": ""
 },
 {
   "A": "",
   "B": ""
 },
 {
   "A": "",
   "B": ""
 },
 {
   "A": "",
   "B": ""
 },
 {
   "A": "",
   "B": ""
 },
 {
   "A": "",
   "B": ""
 },
 {
   "A": "",
   "B": ""
 },
 {
   "A": "",
   "B": ""
 },
 {
   "A": "",
   "B": ""
 },
 {
   "A": "",
   "B": ""
 },
 {
   "A": "",
   "B": ""
 },
 {
   "A": "",
   "B": ""
 },
 {
   "A": "",
   "B": ""
 },
 {
   "A": "",
   "B": ""
 },
 {
   "A": "",
   "B": ""
 },
 {
   "A": "",
   "B": ""
 },
 {
   "A": "",
   "B": ""
 },
 {
   "A": "",
   "B": ""
 },
 {
   "A": "",
   "B": ""
 },
 {
   "A": "",
   "B": ""
 },
 {
   "A": "",
   "B": ""
 },
 {
   "A": "",
   "B": ""
 },
 {
   "A": "",
   "B": ""
 },
 {
   "A": "",
   "B": ""
 },
 {
   "A": "",
   "B": ""
 },
 {
   "A": "",
   "B": ""
 },
 {
   "A": "",
   "B": ""
 },
 {
   "A": "",
   "B": ""
 },
 {
   "A": "",
   "B": ""
 },
 {
   "A": "",
   "B": ""
 },
 {
   "A": "",
   "B": ""
 },
 {
   "A": "",
   "B": ""
 },
 {
   "A": "",
   "B": ""
 },
 {
   "A": "",
   "B": ""
 },
 {
   "A": "",
   "B": ""
 },
 {
   "A": "",
   "B": ""
 },
 {
   "A": "",
   "B": ""
 },
 {
   "A": "",
   "B": ""
 },
 {
   "A": "",
   "B": ""
 },
 {
   "A": "",
   "B": ""
 },
 {
   "A": "",
   "B": ""
 },
 {
   "A": "",
   "B": ""
 },
 {
   "A": "",
   "B": ""
 },
 {
   "A": "",
   "B": ""
 },
 {
   "A": "",
   "B": ""
 },
 {
   "A": "",
   "B": ""
 },
 {
   "A": "",
   "B": ""
 },
 {
   "A": "",
   "B": ""
 },
 {
   "A": "",
   "B": ""
 },
 {
   "A": "",
   "B": ""
 },
 {
   "A": "",
   "B": ""
 },
 {
   "A": "",
   "B": ""
 },
 {
   "A": "",
   "B": ""
 },
 {
   "A": "",
   "B": ""
 },
 {
   "A": "",
   "B": ""
 },
 {
   "A": "",
   "B": ""
 },
 {
   "A": "",
   "B": ""
 },
 {
   "A": "",
   "B": ""
 },
 {
   "A": "",
   "B": ""
 },
 {
   "A": "",
   "B": ""
 },
 {
   "A": "",
   "B": ""
 },
 {
   "A": "",
   "B": ""
 },
 {
   "A": "",
   "B": ""
 },
 {
   "A": "",
   "B": ""
 },
 {
   "A": "",
   "B": ""
 },
 {
   "A": "",
   "B": ""
 },
 {
   "A": "",
   "B": ""
 },
 {
   "A": "",
   "B": ""
 },
 {
   "A": "",
   "B": ""
 },
 {
   "A": "",
   "B": ""
 },
 {
   "A": "",
   "B": ""
 },
 {
   "A": "",
   "B": ""
 },
 {
   "A": "",
   "B": ""
 },
 {
   "A": "",
   "B": ""
 },
 {
   "A": "",
   "B": ""
 },
 {
   "A": "",
   "B": ""
 },
 {
   "A": "",
   "B": ""
 },
 {
   "A": "",
   "B": ""
 },
 {
   "A": "",
   "B": ""
 },
 {
   "A": "",
   "B": ""
 },
 {
   "A": "",
   "B": ""
 },
 {
   "A": "",
   "B": ""
 },
 {
   "A": "",
   "B": ""
 },
 {
   "A": "",
   "B": ""
 },
 {
   "A": "",
   "B": ""
 },
 {
   "A": "",
   "B": ""
 },
 {
   "A": "",
   "B": ""
 },
 {
   "A": "",
   "B": ""
 },
 {
   "A": "",
   "B": ""
 },
 {
   "A": "",
   "B": ""
 },
 {
   "A": "",
   "B": ""
 },
 {
   "A": "",
   "B": ""
 },
 {
   "A": "",
   "B": ""
 },
 {
   "A": "",
   "B": ""
 },
 {
   "A": "",
   "B": ""
 },
 {
   "A": "",
   "B": ""
 },
 {
   "A": "",
   "B": ""
 },
 {
   "A": "",
   "B": ""
 },
 {
   "A": "",
   "B": ""
 },
 {
   "A": "",
   "B": ""
 },
 {
   "A": "",
   "B": ""
 },
 {
   "A": "",
   "B": ""
 },
 {
   "A": "",
   "B": ""
 },
 {
   "A": "",
   "B": ""
 },
 {
   "A": "",
   "B": ""
 },
 {
   "A": "",
   "B": ""
 },
 {
   "A": "",
   "B": ""
 },
 {
   "A": "",
   "B": ""
 },
 {
   "A": "",
   "B": ""
 },
 {
   "A": "",
   "B": ""
 },
 {
   "A": "",
   "B": ""
 },
 {
   "A": "",
   "B": ""
 },
 {
   "A": "",
   "B": ""
 },
 {
   "A": "",
   "B": ""
 },
 {
   "A": "",
   "B": ""
 },
 {
   "A": "",
   "B": ""
 },
 {
   "A": "",
   "B": ""
 },
 {
   "A": "",
   "B": ""
 },
 {
   "A": "",
   "B": ""
 },
 {
   "A": "",
   "B": ""
 },
 {
   "A": "",
   "B": ""
 },
 {
   "A": "",
   "B": ""
 },
 {
   "A": "",
   "B": ""
 },
 {
   "A": "",
   "B": ""
 },
 {
   "A": "",
   "B": ""
 },
 {
   "A": "",
   "B": ""
 },
 {
   "A": "",
   "B": ""
 },
 {
   "A": "",
   "B": ""
 },
 {
   "A": "",
   "B": ""
 },
 {
   "A": "",
   "B": ""
 },
 {
   "A": "",
   "B": ""
 },
 {
   "A": "",
   "B": ""
 },
 {
   "A": "",
   "B": ""
 },
 {
   "A": "",
   "B": ""
 },
 {
   "A": "",
   "B": ""
 },
 {
   "A": "",
   "B": ""
 },
 {
   "A": "",
   "B": ""
 },
 {
   "A": "",
   "B": ""
 },
 {
   "A": "",
   "B": ""
 },
 {
   "A": "",
   "B": ""
 },
 {
   "A": "",
   "B": ""
 },
 {
   "A": "",
   "B": ""
 },
 {
   "A": "",
   "B": ""
 },
 {
   "A": "",
   "B": ""
 },
 {
   "A": "",
   "B": ""
 },
 {
   "A": "",
   "B": ""
 },
 {
   "A": "",
   "B": ""
 },
 {
   "A": "",
   "B": ""
 },
 {
   "A": "",
   "B": ""
 },
 {
   "A": "",
   "B": ""
 },
 {
   "A": "",
   "B": ""
 },
 {
   "A": "",
   "B": ""
 },
 {
   "A": "",
   "B": ""
 },
 {
   "A": "",
   "B": ""
 },
 {
   "A": "",
   "B": ""
 },
 {
   "A": "",
   "B": ""
 },
 {
   "A": "",
   "B": ""
 },
 {
   "A": "",
   "B": ""
 },
 {
   "A": "",
   "B": ""
 },
 {
   "A": "",
   "B": ""
 },
 {
   "A": "",
   "B": ""
 },
 {
   "A": "",
   "B": ""
 }
]